crf_query_xtract/__init__.py
crf_query_xtract/kx_ca.pkl
crf_query_xtract/kx_da.pkl
crf_query_xtract/kx_de.pkl
crf_query_xtract/kx_en.pkl
crf_query_xtract/kx_eu.pkl
crf_query_xtract/kx_fr.pkl
crf_query_xtract/kx_gl.pkl
crf_query_xtract/kx_it.pkl
crf_query_xtract/kx_pt.pkl
crf_query_xtract/version.py
crf_query_xtract-0.1.2.dist-info/METADATA
crf_query_xtract-0.1.2.dist-info/WHEEL
crf_query_xtract-0.1.2.dist-info/top_level.txt
crf_query_xtract-0.1.2.dist-info/RECORD
