Metadata-Version: 2.1
Name: crf-query-xtract
Version: 0.1.2
Home-page: https://github.com/TigreGotico/crf_query_xtract
Author: JarbasAi
Author-email: jarbasai@mailfence.com
Classifier: Programming Language :: Python :: 3
Classifier: License :: OSI Approved :: MIT License
Classifier: Operating System :: OS Independent
Requires-Python: >=3.9
Requires-Dist: ovos-utils
Requires-Dist: nltk
Requires-Dist: joblib
Requires-Dist: sklearn-crfsuite
Requires-Dist: crf-query-xtract
